tmm/__init__.py
tmm/main.py
tmm/chains/0gchain.json
tmm/chains/babylon.json
tmm/chains/celestia.json
tmm/chains/cosmos.json
tmm/chains/dymension.json
tmm/chains/mantra.json
tmm/chains/neutron.json
tmm/chains/nillion.json
tmm/chains/terra.json
tmm/chains/xion.json
tmm_monitor-1.1.7.dist-info/METADATA
tmm_monitor-1.1.7.dist-info/WHEEL
tmm_monitor-1.1.7.dist-info/entry_points.txt
tmm_monitor-1.1.7.dist-info/top_level.txt
tmm_monitor-1.1.7.dist-info/RECORD
