Metadata-Version: 2.4
Name: tmm-monitor
Version: 1.1.7
Summary: Tendermint Metrics Monitor - A TUI for monitoring blockchain metrics
Home-page: https://github.com/bert2002/tmm
Author: 
Author-email: 
Classifier: Programming Language :: Python :: 3
Classifier: License :: OSI Approved :: MIT License
Classifier: Operating System :: OS Independent
Classifier: Environment :: Console
Requires-Python: >=3.9
Requires-Dist: textual==0.79.1
Requires-Dist: plotext==5.2.8
Dynamic: classifier
Dynamic: description
Dynamic: description-content-type
Dynamic: home-page
Dynamic: requires-dist
Dynamic: requires-python
Dynamic: summary
